py_neuromodulation/__init__.py
py_neuromodulation/default_settings.yaml
py_neuromodulation/grid_cortex.tsv
py_neuromodulation/grid_subcortex.tsv
py_neuromodulation/lsl_api.cfg
py_neuromodulation/run_gui.py
py_neuromodulation/ConnectivityDecoding/Automated Anatomical Labeling 3 (Rolls 2020).nii
py_neuromodulation/ConnectivityDecoding/_get_grid_hull.m
py_neuromodulation/ConnectivityDecoding/_get_grid_whole_brain.py
py_neuromodulation/ConnectivityDecoding/_helper_write_connectome.py
py_neuromodulation/ConnectivityDecoding/mni_coords_cortical_surface.mat
py_neuromodulation/ConnectivityDecoding/mni_coords_whole_brain.mat
py_neuromodulation/ConnectivityDecoding/rmap_func_all.nii
py_neuromodulation/ConnectivityDecoding/rmap_struc.nii
py_neuromodulation/analysis/RMAP.py
py_neuromodulation/analysis/__init__.py
py_neuromodulation/analysis/decode.py
py_neuromodulation/analysis/feature_reader.py
py_neuromodulation/analysis/plots.py
py_neuromodulation/analysis/stats.py
py_neuromodulation/data/README
py_neuromodulation/data/dataset_description.json
py_neuromodulation/data/participants.json
py_neuromodulation/data/participants.tsv
py_neuromodulation/data/sub-testsub/ses-EphysMedOff/sub-testsub_ses-EphysMedOff_scans.tsv
py_neuromodulation/data/sub-testsub/ses-EphysMedOff/ieeg/sub-testsub_ses-EphysMedOff_space-mni_coordsystem.json
py_neuromodulation/data/sub-testsub/ses-EphysMedOff/ieeg/sub-testsub_ses-EphysMedOff_space-mni_electrodes.tsv
py_neuromodulation/data/sub-testsub/ses-EphysMedOff/ieeg/sub-testsub_ses-EphysMedOff_task-gripforce_run-0_channels.tsv
py_neuromodulation/data/sub-testsub/ses-EphysMedOff/ieeg/sub-testsub_ses-EphysMedOff_task-gripforce_run-0_ieeg.eeg
py_neuromodulation/data/sub-testsub/ses-EphysMedOff/ieeg/sub-testsub_ses-EphysMedOff_task-gripforce_run-0_ieeg.json
py_neuromodulation/data/sub-testsub/ses-EphysMedOff/ieeg/sub-testsub_ses-EphysMedOff_task-gripforce_run-0_ieeg.vhdr
py_neuromodulation-0.1.4.dist-info/METADATA
py_neuromodulation-0.1.4.dist-info/WHEEL
py_neuromodulation-0.1.4.dist-info/entry_points.txt
py_neuromodulation-0.1.4.dist-info/licenses/LICENSE
py_neuromodulation-0.1.4.dist-info/RECORD
