Metadata-Version: 2.4
Name: py_neuromodulation
Version: 0.1.4
Summary: Real-time analysis of intracranial neurophysiology recordings.
Project-URL: Homepage, https://neuromodulation.github.io/py_neuromodulation/
Project-URL: Documentation, https://neuromodulation.github.io/py_neuromodulation/
Project-URL: Repository, https://github.com/neuromodulation/py_neuromodulation
Project-URL: Issues, https://github.com/neuromodulation/py_neuromodulation/issues
Author-email: Timon Merk <timon.merk@charite.de>
Maintainer: Timon Merk
License: MIT License
License-File: LICENSE
Keywords: dbs,deep-brain-stimulation,ecog,eeg,electrocorticography,ieeg,machine-learning,real-time
Classifier: Development Status :: 2 - Pre-Alpha
Classifier: License :: OSI Approved :: MIT License
Classifier: Programming Language :: Python
Classifier: Topic :: Software Development :: Libraries :: Python Modules
Requires-Python: >=3.12
Requires-Dist: cbor2>=5.6.4
Requires-Dist: fastapi
Requires-Dist: fooof
Requires-Dist: imbalanced-learn
Requires-Dist: joblib>=1.3.2
Requires-Dist: llvmlite>=0.43.0
Requires-Dist: matplotlib>=3.9.0
Requires-Dist: mne
Requires-Dist: mne-bids>=0.8
Requires-Dist: mne-connectivity
Requires-Dist: mne-lsl>=1.2.0
Requires-Dist: mrmr-selection
Requires-Dist: msgpack
Requires-Dist: msgpack>=1.1.0
Requires-Dist: nibabel>=5.3.2
Requires-Dist: nolds>=0.6.1
Requires-Dist: numba>=0.60.0
Requires-Dist: numpy>=1.21.2
Requires-Dist: numpy>=2.0.0
Requires-Dist: pandas>=2.0.0
Requires-Dist: pyarrow>=14.0.2
Requires-Dist: pybispectra>=1.2.0
Requires-Dist: pydantic>=2.7.3
Requires-Dist: pyparrm
Requires-Dist: pyqt6
Requires-Dist: pywebview
Requires-Dist: scikit-learn>=0.24.2
Requires-Dist: scikit-optimize
Requires-Dist: scipy>=1.7.1
Requires-Dist: seaborn>=0.11
Requires-Dist: skops>=0.10.0
Requires-Dist: uvicorn[standard]>=0.30.6
Requires-Dist: uvloop; platform_system != 'Windows'
Provides-Extra: dev
Requires-Dist: notebook; extra == 'dev'
Requires-Dist: pytest-cov; extra == 'dev'
Requires-Dist: pytest-sugar; extra == 'dev'
Requires-Dist: pytest>=8.0.2; extra == 'dev'
Requires-Dist: ruff; extra == 'dev'
Provides-Extra: docs
Requires-Dist: notebook; extra == 'docs'
Requires-Dist: numpydoc; extra == 'docs'
Requires-Dist: pydata-sphinx-theme; extra == 'docs'
Requires-Dist: pytest-cov; extra == 'docs'
Requires-Dist: pytest-sugar; extra == 'docs'
Requires-Dist: pytest>=8.0.2; extra == 'docs'
Requires-Dist: recommonmark; extra == 'docs'
Requires-Dist: ruff; extra == 'docs'
Requires-Dist: sphinx; extra == 'docs'
Requires-Dist: sphinx-gallery; extra == 'docs'
Requires-Dist: sphinx-togglebutton; extra == 'docs'
Provides-Extra: test
Requires-Dist: pytest-xdist; extra == 'test'
Requires-Dist: pytest>=8.0.2; extra == 'test'
